MANIFEST.in
README.rst
setup.py
docs/HISTORY.txt
docs/INSTALL.txt
docs/LICENSE.GPL
docs/LICENSE.txt
monet/__init__.py
monet.calendar.portlet.egg-info/PKG-INFO
monet.calendar.portlet.egg-info/SOURCES.txt
monet.calendar.portlet.egg-info/dependency_links.txt
monet.calendar.portlet.egg-info/entry_points.txt
monet.calendar.portlet.egg-info/namespace_packages.txt
monet.calendar.portlet.egg-info/not-zip-safe
monet.calendar.portlet.egg-info/requires.txt
monet.calendar.portlet.egg-info/top_level.txt
monet/calendar/__init__.py
monet/calendar/portlet/__init__.py
monet/calendar/portlet/configure.zcml
monet/calendar/portlet/monetcalendar.pt
monet/calendar/portlet/monetcalendar.py
monet/calendar/portlet/monetcalendarportlet.pt
monet/calendar/portlet/monetcalendarportlet.py
monet/calendar/portlet/locales/i18n.sh
monet/calendar/portlet/locales/monet.calendar.portlet.pot
monet/calendar/portlet/locales/it/LC_MESSAGES/monet.calendar.portlet.mo
monet/calendar/portlet/locales/it/LC_MESSAGES/monet.calendar.portlet.po
monet/calendar/portlet/profiles/default/metadata.xml
monet/calendar/portlet/profiles/default/portlets.xml
monet/calendar/portlet/tests/__init__.py
monet/calendar/portlet/tests/base.py
monet/calendar/portlet/tests/test_portlet.py