Metadata-Version: 1.0
Name: monet.calendar.portlet
Version: 0.4.0
Summary: Calendar related portlets for the Plone Monet Calendar events suite
Home-page: http://plone.org/products/monet.calendar.star
Author: RedTurtle Technology
Author-email: sviluppoplone@redturtle.it
License: GPL
Keywords: plone plonegov calendar event monet
Platform: UNKNOWN
Classifier: Framework :: Plone
Classifier: Framework :: Plone :: 4.2
Classifier: Framework :: Plone :: 4.3
Classifier: Programming Language :: Python
